fssa/__init__.py
fssa/fssa.py
fssa/optimize.py
fssa/test/__init__.py
fssa/test/test_fss.py
fssa-0.7.6.dist-info/DESCRIPTION.rst
fssa-0.7.6.dist-info/METADATA
fssa-0.7.6.dist-info/RECORD
fssa-0.7.6.dist-info/WHEEL
fssa-0.7.6.dist-info/entry_points.txt
fssa-0.7.6.dist-info/metadata.json
fssa-0.7.6.dist-info/namespace_packages.txt
fssa-0.7.6.dist-info/top_level.txt
