Metadata-Version: 2.0
Name: fssa
Version: 0.7.6
Summary: Scientific Python package for finite-size scaling analysis at phase transitions
Home-page: http://pyfssa.readthedocs.org
Author: Andreas Sorge
Author-email: pyfssa@asorge.de
License: isc
Platform: UNKNOWN
Classifier: Development Status :: 3 - Alpha
Classifier: Intended Audience :: Science/Research
Classifier: License :: OSI Approved :: ISC License (ISCL)
Classifier: Programming Language :: Python
Classifier: Programming Language :: Python :: 2.7
Classifier: Programming Language :: Python :: 3.4
Classifier: Programming Language :: Python :: 3.5
Classifier: Topic :: Scientific/Engineering :: Mathematics
Classifier: Topic :: Scientific/Engineering :: Physics
Requires-Dist: future
Requires-Dist: numpy
Requires-Dist: scipy (>=0.14.0)
